obschart/__init__.py
obschart/api/__init__.py
obschart/api/context.py
obschart/api/node.py
obschart/api/nodes/__init__.py
obschart/api/nodes/application.py
obschart/api/nodes/application_request.py
obschart/api/nodes/chat_channel.py
obschart/api/nodes/client_profile_invitation.py
obschart/api/nodes/image.py
obschart/api/nodes/program.py
obschart/api/nodes/program_invitation.py
obschart/api/nodes/program_module.py
obschart/api/nodes/program_track_action.py
obschart/api/nodes/program_track_action_response.py
obschart/api/nodes/program_track_event.py
obschart/api/nodes/session.py
obschart/api/nodes/tag.py
obschart/api/obschart_api_client.py
obschart/application_request_handler.py
obschart/blocks_action_builder.py
obschart/extract_files.py
obschart/gql/__init__.py
obschart/gql/gql.py
obschart/gql/gql_client.py
obschart/gql/gql_client_transport.py
obschart/obschart_api_transport.py
obschart/obschart_client.py
obschart/py.typed
obschart/step_builder.py
obschart-1.2.0.dist-info/WHEEL
obschart-1.2.0.dist-info/METADATA
obschart-1.2.0.dist-info/RECORD
